{
  "folder": "yp679XUkEdEYNSVY",
  "name": "Focus Fire",
  "type": "rule",
  "img": "icons/skills/targeting/crosshair-pointed-orange.webp",
  "system": {
    "subtype": {},
    "summary": {
      "value": "You command your allies to focus on a target"
    },
    "description": "<p>At the <strong>start of a conflict,</strong> you command all your allies to <strong>focus their attention on a single target</strong> and inflict it with @EFFECT[Compendium.projectfu.actor-effects.6JCfyn7Ewt0AJndC]{Physical Weakness}.</p>",
    "isFavored": {
      "value": false
    },
    "showTitleCard": {
      "value": false
    },
    "isBehavior": {
      "value": false
    },
    "weight": {
      "value": 1
    },
    "hasClock": {
      "value": false
    },
    "progress": {
      "name": "Name",
      "current": 0,
      "step": 1,
      "max": 6
    },
    "source": {
      "value": "FU-AZURE"
    },
    "fuid": "afc-focus-fire"
  },
  "effects": [],
  "ownership": {
    "default": 0,
    "esOkelwPNblkbxW3": 3
  },
  "flags": {
    "projectfu": {
      "favorite": false
    }
  },
  "_stats": {
    "compendiumSource": null,
    "duplicateSource": null,
    "coreVersion": "13.351",
    "systemId": "projectfu",
    "systemVersion": "#{VERSION}#",
    "createdTime": 1731429340899,
    "modifiedTime": 1771078987257,
    "lastModifiedBy": "J5B4HfVqUaCPvzGg",
    "exportSource": null
  },
  "_id": "FFJ4k0iZvhg3W6lN",
  "sort": 100000,
  "_key": "!items!FFJ4k0iZvhg3W6lN"
}
