{
  "folder": "YXxIAFAGV7qohzPK",
  "name": "Astral Hypno",
  "type": "spell",
  "_id": "k6aO5CyVhB2e21Nf",
  "img": "icons/magic/control/sleep-bubble-purple.webp",
  "system": {
    "fuid": "afc-astral-hypno",
    "subtype": {},
    "summary": {
      "value": ""
    },
    "description": "<p>You send the target into a sudden @UUID[Compendium.fu-azure-compendia.effects.j3oBtOJaTjk6dzgN]{Sleep} for <strong>two turns. </strong>However they cannot make a check to recover.</p><ul><li><p><strong>Target</strong>: @EFFECT[Compendium.fu-azure-compendia.effects.j3oBtOJaTjk6dzgN]{Sleep}</p></li></ul>",
    "isFavored": {
      "value": false
    },
    "showTitleCard": {
      "value": false
    },
    "class": {
      "value": "NPC"
    },
    "useWeapon": {
      "accuracy": {
        "value": false
      },
      "damage": {
        "value": false
      },
      "hrZero": {
        "value": false
      }
    },
    "attributes": {
      "primary": {
        "value": "ins"
      },
      "secondary": {
        "value": "mig"
      }
    },
    "accuracy": {
      "value": 0
    },
    "damage": {
      "hasDamage": {
        "value": false
      },
      "value": 0,
      "type": {
        "value": "physical"
      }
    },
    "impdamage": {
      "hasImpDamage": {
        "value": false
      },
      "value": 0,
      "impType": {
        "value": "minor"
      },
      "type": {
        "value": "physical"
      }
    },
    "isBehavior": {
      "value": false
    },
    "weight": {
      "value": 1
    },
    "mpCost": {
      "value": "20"
    },
    "maxTargets": {
      "value": 2
    },
    "target": {
      "value": ""
    },
    "duration": {
      "value": "instantaneous"
    },
    "isOffensive": {
      "value": false
    },
    "source": {
      "value": "FU-AZURE"
    },
    "rollInfo": {
      "useWeapon": {
        "hrZero": {
          "value": false
        }
      },
      "attributes": {
        "primary": {
          "value": "ins"
        },
        "secondary": {
          "value": "mig"
        }
      },
      "accuracy": {
        "value": 0
      },
      "damage": {
        "hasDamage": {
          "value": false
        },
        "value": 0,
        "type": {
          "value": "physical"
        }
      }
    },
    "hasRoll": {
      "value": false
    },
    "opportunity": ""
  },
  "effects": [],
  "sort": 0,
  "ownership": {
    "default": 0,
    "esOkelwPNblkbxW3": 3
  },
  "flags": {
    "projectfu": {
      "favorite": false
    }
  },
  "_stats": {
    "compendiumSource": null,
    "duplicateSource": null,
    "coreVersion": "13.351",
    "systemId": "projectfu",
    "systemVersion": "#{VERSION}#",
    "createdTime": 1731434282126,
    "modifiedTime": 1771102517433,
    "lastModifiedBy": "J5B4HfVqUaCPvzGg",
    "exportSource": null
  },
  "_key": "!items!k6aO5CyVhB2e21Nf"
}
